odoo8_addon_l10n_ar_electronic_invoice_storage_rg1361-8.0.1.0.0-py2.7-nspkg.pth
odoo_addons/l10n_ar_electronic_invoice_storage_rg1361/product.py
odoo_addons/l10n_ar_electronic_invoice_storage_rg1361/.gitignore
odoo_addons/l10n_ar_electronic_invoice_storage_rg1361/__openerp__.py
odoo_addons/l10n_ar_electronic_invoice_storage_rg1361/tablas.txt
odoo_addons/l10n_ar_electronic_invoice_storage_rg1361/partner.py
odoo_addons/l10n_ar_electronic_invoice_storage_rg1361/fixed_width.py
odoo_addons/l10n_ar_electronic_invoice_storage_rg1361/account_invoice_view.xml
odoo_addons/l10n_ar_electronic_invoice_storage_rg1361/res_currency.py
odoo_addons/l10n_ar_electronic_invoice_storage_rg1361/__init__.py
odoo_addons/l10n_ar_electronic_invoice_storage_rg1361/product_view.xml
odoo_addons/l10n_ar_electronic_invoice_storage_rg1361/invoice.py
odoo_addons/l10n_ar_electronic_invoice_storage_rg1361/res_currency_view.xml
odoo_addons/l10n_ar_electronic_invoice_storage_rg1361/partner_view.xml
odoo_addons/l10n_ar_electronic_invoice_storage_rg1361/wizard/fixed_width_dicts.py
odoo_addons/l10n_ar_electronic_invoice_storage_rg1361/wizard/create_sired_files.py
odoo_addons/l10n_ar_electronic_invoice_storage_rg1361/wizard/__init__.py
odoo_addons/l10n_ar_electronic_invoice_storage_rg1361/wizard/create_sired_files_view.xml
odoo8_addon_l10n_ar_electronic_invoice_storage_rg1361-8.0.1.0.0.dist-info/top_level.txt
odoo8_addon_l10n_ar_electronic_invoice_storage_rg1361-8.0.1.0.0.dist-info/WHEEL
odoo8_addon_l10n_ar_electronic_invoice_storage_rg1361-8.0.1.0.0.dist-info/RECORD
odoo8_addon_l10n_ar_electronic_invoice_storage_rg1361-8.0.1.0.0.dist-info/metadata.json
odoo8_addon_l10n_ar_electronic_invoice_storage_rg1361-8.0.1.0.0.dist-info/DESCRIPTION.rst
odoo8_addon_l10n_ar_electronic_invoice_storage_rg1361-8.0.1.0.0.dist-info/METADATA
odoo8_addon_l10n_ar_electronic_invoice_storage_rg1361-8.0.1.0.0.dist-info/namespace_packages.txt
