Metadata-Version: 2.0
Name: odoo8-addon-l10n-ar-electronic-invoice-storage-rg1361
Version: 8.0.1.0.0
Summary: l10n_ar_electronic_invoice_storage_rg1361
Home-page: UNKNOWN
Author: UNKNOWN
Author-email: UNKNOWN
License: UNKNOWN
Platform: UNKNOWN
Requires-Dist: odoo (<9.0a,>=8.0a)
Requires-Dist: odoo8-addon-base-vat-ar
Requires-Dist: odoo8-addon-l10n-ar-point-of-sale
Requires-Dist: odoo8-addon-l10n-ar-wsfe
Classifier: Programming Language :: Python :: 2.7
Classifier: Framework :: Odoo
